{
  "posts": [
    {
      "id": 0,
      "description": "test1",
      "external_url": "https://forum.openzeppelin.com/t/create-an-nft-and-deploy-to-a-public-testnet-using-truffle/2961",
      "animation_url": "https://caterhive.com/cat/1.html",
      "name": "test1"
    },
    {
      "id": 1,
      "description": "test2",
      "external_url": "https://forum.openzeppelin.com/t/create-an-nft-and-deploy-to-a-public-testnet-using-truffle/2961",
      "animation_url": "https://caterhive.com/cat/2.html",
      "name": "test2"
    },
    {
      "id": 2,
      "description": "test3",
      "external_url": "https://forum.openzeppelin.com/t/create-an-nft-and-deploy-to-a-public-testnet-using-truffle/2961",
      "animation_url": "https://caterhive.com/cat/3.html",
      "name": "test3"
    },
    {
      "id": 3,
      "description": "test2",
      "external_url": "https://forum.openzeppelin.com/t/create-an-nft-and-deploy-to-a-public-testnet-using-truffle/2961",
      "animation_url": "https://caterhive.com/cat/4.html",
      "name": "test2"
    },
    {
      "id": 4,
      "description": "test2",
      "external_url": "https://forum.openzeppelin.com/t/create-an-nft-and-deploy-to-a-public-testnet-using-truffle/2961",
      "animation_url": "https://caterhive.com/cat/5.html",
      "name": "test2"
    },
    {
      "id": 5,
      "description": "test2",
      "external_url": "https://forum.openzeppelin.com/t/create-an-nft-and-deploy-to-a-public-testnet-using-truffle/2961",
      "animation_url": "https://caterhive.com/cat/6.html",
      "name": "test2"
    },
    {
      "id": 6,
      "description": "test2",
      "external_url": "https://forum.openzeppelin.com/t/create-an-nft-and-deploy-to-a-public-testnet-using-truffle/2961",
      "animation_url": "https://caterhive.com/cat/7.html",
      "name": "test2"
    },
    {
      "id": 7,
      "description": "test2",
      "external_url": "https://forum.openzeppelin.com/t/create-an-nft-and-deploy-to-a-public-testnet-using-truffle/2961",
      "animation_url": "https://caterhive.com/cat/8.html",
      "name": "test2"
    },
    {
      "id": 8,
      "description": "test2",
      "external_url": "https://forum.openzeppelin.com/t/create-an-nft-and-deploy-to-a-public-testnet-using-truffle/2961",
      "animation_url": "https://caterhive.com/cat/9.html",
      "name": "test2"
    }
  ]
}